wedata/__init__.py
wedata/api.py
wedata/checker.py
wedata/client.py
wedata/client_local.py
wedata/config.py
wedata/utils.py
wedata-0.0.22.dist-info/METADATA
wedata-0.0.22.dist-info/WHEEL
wedata-0.0.22.dist-info/top_level.txt
wedata-0.0.22.dist-info/RECORD
